<?xml version = '1.0' encoding = 'UTF-8'?>
<Diagram class="oracle.dbtools.crest.swingui.logical.DPVLogical" name="Logical" id="1C92C2B1-D40A-3E09-0DC8-E3525D1909EB">
<createdBy>andre.hugo.b.silva</createdBy>
<modifiedBy>andre.hugo.b.silva</modifiedBy>
<createdTime>2021-11-11 23:01:44 UTC</createdTime>
<autoRoute>false</autoRoute>
<boxInbox>true</boxInbox>
<showLegend>false</showLegend>
<showLabels>false</showLabels>
<showRelAttributes>false</showRelAttributes>
<gridEnabled>false</gridEnabled>
<showGrid>false</showGrid>
<diagramColor>-1</diagramColor>
<display>false</display>
<notation>2</notation>
<objectViews>
<OView class="oracle.dbtools.crest.swingui.logical.TVEntity" oid="181824C7-C081-1EA8-9341-BDF8E5AA415A" otype="Entity" vid="F12D910C-4304-7FCD-A312-C2D3C7E00020">
<hideElementsInCurrentOnly>false</hideElementsInCurrentOnly>
<bounds x="140" y="801" width="360" height="133"/>
</OView>
<OView class="oracle.dbtools.crest.swingui.logical.TVEntity" oid="1F7CB8C1-F554-80CE-2970-CD3F679C4760" otype="Entity" vid="105A7FED-3D39-5502-51F5-95D2395D489B">
<hideElementsInCurrentOnly>false</hideElementsInCurrentOnly>
<bounds x="606" y="135" width="374" height="144"/>
</OView>
<OView class="oracle.dbtools.crest.swingui.logical.TVEntity" oid="30B24506-6DAB-845B-977E-927411F6DFCC" otype="Entity" vid="7B18728F-2101-8B80-5BBB-9378E88DB735">
<hideElementsInCurrentOnly>false</hideElementsInCurrentOnly>
<bounds x="1073" y="370" width="369" height="157"/>
</OView>
<OView class="oracle.dbtools.crest.swingui.logical.TVEntity" oid="3F7BD3E8-470D-24BE-11F9-60014EC70405" otype="Entity" vid="DF74EC0E-E8B0-0B3E-260E-9E61C01E96F3">
<hideElementsInCurrentOnly>false</hideElementsInCurrentOnly>
<bounds x="136" y="127" width="363" height="330"/>
</OView>
<OView class="oracle.dbtools.crest.swingui.logical.TVEntity" oid="775D53F7-CE12-165D-5DB0-452D9DB94C91" otype="Entity" vid="BEC83811-B469-B98E-83BF-589D84180A4F">
<hideElementsInCurrentOnly>false</hideElementsInCurrentOnly>
<bounds x="139" y="564" width="363" height="160"/>
</OView>
<OView class="oracle.dbtools.crest.swingui.TVNote" oid="7CA47F06-2E26-262B-A4DB-FF8C527AEF64" otype="Note" vid="DF893A4C-3B6A-D0F4-F51F-5447824FD25E">
<hideElementsInCurrentOnly>false</hideElementsInCurrentOnly>
<bounds x="135" y="4" width="365" height="97"/>
<comment>ANDRÉ HUGO BASTOS DA SILVA - RM 88588
MATHEUS FERREIRA SANTANA - RM 88241
THALES CASTELLANI - RM 86692
OSWALDO GOMES MOREIRA - RM 88526</comment>
</OView>
<OView class="oracle.dbtools.crest.swingui.logical.TVEntity" oid="87E85BD7-BA45-C9EB-E2EB-E5BF7FF85FE3" otype="Entity" vid="B4CE16F4-F12E-08D4-4D6C-6CA33890FE6D">
<hideElementsInCurrentOnly>false</hideElementsInCurrentOnly>
<bounds x="608" y="633" width="380" height="160"/>
</OView>
<OView class="oracle.dbtools.crest.swingui.logical.TVEntity" oid="CFF2004E-3369-9917-50F5-EDD62BFCEB45" otype="Entity" vid="AB955ED5-86D4-6219-B2B6-5A584B8B6AAB">
<hideElementsInCurrentOnly>false</hideElementsInCurrentOnly>
<bounds x="610" y="375" width="375" height="157"/>
</OView>
</objectViews>
<connectors>
<Connector class="oracle.dbtools.crest.swingui.logical.TVRelation" oid="06468622-B08C-2059-77B0-699C732F026C" otype="Relation" vid_source="AB955ED5-86D4-6219-B2B6-5A584B8B6AAB" vid_target="105A7FED-3D39-5502-51F5-95D2395D489B">
<hideElementsInCurrentOnly>false</hideElementsInCurrentOnly>
<backgroundColor>-16777216</backgroundColor>
<lineWidth>1</lineWidth>
<points>
<point x="795" y="375"/>
<point x="795" y="279"/>
</points>
</Connector>
<Connector class="oracle.dbtools.crest.swingui.logical.TVRelation" oid="0ACCA376-3419-A5DE-684D-518BC9D9F417" otype="Relation" vid_source="DF74EC0E-E8B0-0B3E-260E-9E61C01E96F3" vid_target="105A7FED-3D39-5502-51F5-95D2395D489B">
<hideElementsInCurrentOnly>false</hideElementsInCurrentOnly>
<backgroundColor>-16777216</backgroundColor>
<lineWidth>1</lineWidth>
<points>
<point x="499" y="207"/>
<point x="606" y="207"/>
</points>
</Connector>
<Connector class="oracle.dbtools.crest.swingui.logical.TVRelation" oid="667ED7DD-FB79-FEAB-0DED-66D9EA96039B" otype="Relation" vid_source="BEC83811-B469-B98E-83BF-589D84180A4F" vid_target="F12D910C-4304-7FCD-A312-C2D3C7E00020">
<hideElementsInCurrentOnly>false</hideElementsInCurrentOnly>
<backgroundColor>-16777216</backgroundColor>
<lineWidth>1</lineWidth>
<points>
<point x="320" y="724"/>
<point x="320" y="801"/>
</points>
</Connector>
<Connector class="oracle.dbtools.crest.swingui.logical.TVRelation" oid="67F80DC5-2E25-A8B4-5284-ABE607D94D93" otype="Relation" vid_source="AB955ED5-86D4-6219-B2B6-5A584B8B6AAB" vid_target="B4CE16F4-F12E-08D4-4D6C-6CA33890FE6D">
<hideElementsInCurrentOnly>false</hideElementsInCurrentOnly>
<backgroundColor>-16777216</backgroundColor>
<lineWidth>1</lineWidth>
<points>
<point x="797" y="532"/>
<point x="797" y="633"/>
</points>
</Connector>
<Connector class="oracle.dbtools.crest.swingui.logical.TVRelation" oid="9C0241CA-1540-B872-5A46-97256F50DC9F" otype="Relation" vid_source="BEC83811-B469-B98E-83BF-589D84180A4F" vid_target="B4CE16F4-F12E-08D4-4D6C-6CA33890FE6D">
<hideElementsInCurrentOnly>false</hideElementsInCurrentOnly>
<backgroundColor>-16777216</backgroundColor>
<lineWidth>1</lineWidth>
<points>
<point x="502" y="678"/>
<point x="608" y="678"/>
</points>
</Connector>
<Connector class="oracle.dbtools.crest.swingui.logical.TVRelation" oid="AE366C44-69F4-FF5C-F890-1413B97873A5" otype="Relation" vid_source="AB955ED5-86D4-6219-B2B6-5A584B8B6AAB" vid_target="7B18728F-2101-8B80-5BBB-9378E88DB735">
<hideElementsInCurrentOnly>false</hideElementsInCurrentOnly>
<backgroundColor>-16777216</backgroundColor>
<lineWidth>1</lineWidth>
<points>
<point x="985" y="451"/>
<point x="1073" y="451"/>
</points>
</Connector>
<Connector class="oracle.dbtools.crest.swingui.logical.TVRelation" oid="E274D379-50D3-9AAA-60A9-082599D3F9AC" otype="Relation" vid_source="DF74EC0E-E8B0-0B3E-260E-9E61C01E96F3" vid_target="BEC83811-B469-B98E-83BF-589D84180A4F">
<hideElementsInCurrentOnly>false</hideElementsInCurrentOnly>
<backgroundColor>-16777216</backgroundColor>
<lineWidth>1</lineWidth>
<points>
<point x="319" y="457"/>
<point x="319" y="564"/>
</points>
</Connector>
</connectors>
</Diagram>
